LICENSE
MANIFEST.in
README.md
requirements.txt
setup.cfg
setup.py
ftrack_query/__init__.py
ftrack_query/abstract.py
ftrack_query/event.py
ftrack_query/exception.py
ftrack_query/query.py
ftrack_query/type_hints.py
ftrack_query/utils.py
ftrack_query.egg-info/PKG-INFO
ftrack_query.egg-info/SOURCES.txt
ftrack_query.egg-info/dependency_links.txt
ftrack_query.egg-info/requires.txt
ftrack_query.egg-info/top_level.txt