Metadata-Version: 2.1
Name: ftrack-query
Version: 2.0.0
Summary: Easy query generation for the FTrack API.
Home-page: https://github.com/huntfx/ftrack-query
Download-URL: https://github.com/huntfx/ftrack-query/archive/2.0.0.tar.gz
Author: Peter Hunt
Author-email: peter@huntfx.uk
License: MIT
Project-URL: Documentation, https://github.com/huntfx/ftrack-query
Project-URL: Source, https://github.com/huntfx/ftrack-query
Project-URL: Issues, https://github.com/huntfx/ftrack-query/issues
Keywords: ftrack,api,query,vfx
Classifier: Development Status :: 5 - Production/Stable
Classifier: Intended Audience :: Developers
Classifier: License :: OSI Approved :: MIT License
Classifier: Operating System :: Microsoft :: Windows
Classifier: Operating System :: POSIX :: Linux
Classifier: Programming Language :: Python
Classifier: Programming Language :: Python :: 2
Classifier: Programming Language :: Python :: 2.7
Classifier: Programming Language :: Python :: 3
Classifier: Programming Language :: Python :: 3.6
Classifier: Programming Language :: Python :: 3.7
Classifier: Programming Language :: Python :: 3.8
Classifier: Programming Language :: Python :: 3.9
Classifier: Programming Language :: Python :: 3.10
Classifier: Programming Language :: Python :: 3.11
Classifier: Programming Language :: Python :: 3.12
Classifier: Programming Language :: Python :: 3.13
Requires-Python: >=2.7
License-File: LICENSE
